playwright_mcp_fetch/__init__.py
playwright_mcp_fetch/fetcher.py
playwright_mcp_fetch/index.py
playwright_mcp_fetch/server.py
playwright_mcp_fetch/types.py
playwright_mcp_fetch-0.1.5.dist-info/METADATA
playwright_mcp_fetch-0.1.5.dist-info/WHEEL
playwright_mcp_fetch-0.1.5.dist-info/entry_points.txt
playwright_mcp_fetch-0.1.5.dist-info/licenses/LICENSE
playwright_mcp_fetch-0.1.5.dist-info/RECORD
