Metadata-Version: 2.4
Name: playwright-mcp-fetch
Version: 0.1.5
Summary: A MCP server with playwright fetch tools
Author-email: Dewei Yen <k@funmula.com>
License: MIT
License-File: LICENSE
Requires-Python: >=3.10
Requires-Dist: aiohttp>=3.9.0
Requires-Dist: beautifulsoup4>=4.12.0
Requires-Dist: fastapi>=0.104.0
Requires-Dist: html2text>=2024.2.26
Requires-Dist: mcp>=1.4.1
Requires-Dist: playwright>=1.40.0
Requires-Dist: pydantic>=2.0.0
Requires-Dist: python-dotenv>=1.0.0
Requires-Dist: sse-starlette>=1.6.5
Requires-Dist: uvicorn>=0.24.0
